setup.py
recaptcha/__init__.py
recaptcha/client.py
recaptcha2_python3.egg-info/PKG-INFO
recaptcha2_python3.egg-info/SOURCES.txt
recaptcha2_python3.egg-info/dependency_links.txt
recaptcha2_python3.egg-info/not-zip-safe
recaptcha2_python3.egg-info/top_level.txt