Metadata-Version: 1.0
Name: recaptcha2-python3
Version: 0.1
Summary: Python3 client for Recaptcha v2
Home-page: http://github.com/sb89/recaptcha2_python3
Author: Steven Blake
Author-email: s.blake.08@aberdeen.ac.uk
License: MIT
Platform: UNKNOWN
